pytram/__init__.py
pytram/messaging/__init__.py
pytram/messaging/base.py
pytram/messaging/rabbitmq.py
pytram/persistence/__init__.py
pytram/persistence/memory.py
pytram/registry/__init__.py
pytram/registry/command.py
pytram/registry/event.py
pytram/saga/__init__.py
pytram/saga/instance.py
pytram/saga/orchestrator.py
pytram/saga/step.py
pytram_saga-0.2.11.dist-info/licenses/LICENSE
pytram_saga-0.2.11.dist-info/METADATA
pytram_saga-0.2.11.dist-info/WHEEL
pytram_saga-0.2.11.dist-info/top_level.txt
pytram_saga-0.2.11.dist-info/RECORD
