Metadata-Version: 2.4
Name: pytram-saga
Version: 0.2.11
Summary: Saga orchestration framework inspired by Eventuate Tram
Requires-Python: >=3.13
License-File: LICENSE
Requires-Dist: aio-pika>=9.5.5
Requires-Dist: aiosqlite>=0.21.0
Requires-Dist: pyfaulttolerance==0.1.3
Requires-Dist: sqlmodel>=0.0.24
Dynamic: license-file
